brain_games/__init__.py
brain_games/cli.py
brain_games/scripts/__init__.py
brain_games/scripts/brain-calc.py
brain_games/scripts/brain_even.py
brain_games/scripts/brain_games.py
python_project_lvl1-0.2.0.dist-info/entry_points.txt
python_project_lvl1-0.2.0.dist-info/WHEEL
python_project_lvl1-0.2.0.dist-info/METADATA
python_project_lvl1-0.2.0.dist-info/RECORD
